LICENSE
README.md
setup.cfg
setup.py
pyvantage/__init__.py
pyvantage.egg-info/PKG-INFO
pyvantage.egg-info/SOURCES.txt
pyvantage.egg-info/dependency_links.txt
pyvantage.egg-info/top_level.txt
pyvantage.egg-info/zip-safe