Metadata-Version: 2.1
Name: pyvantage
Version: 0.0.40
Summary: Python library for Vantage Controller (for Home Assistant)
Home-page: http://github.com/gjbadros/pyvantage
Author: Greg J. Badros
Author-email: badros@gmail.com
License: MIT
Classifier: Development Status :: 3 - Alpha
Classifier: License :: OSI Approved :: MIT License
Classifier: Operating System :: OS Independent
Classifier: Programming Language :: Python
Classifier: Programming Language :: Python :: 3.4
Classifier: Topic :: Home Automation
Classifier: Topic :: Software Development :: Libraries :: Python Modules
License-File: LICENSE
